{
	"name": "StagingWoSkills",
	"properties": {
		"linkedServiceName": {
			"referenceName": "AzureSqlDatabase1",
			"type": "LinkedServiceReference"
		},
		"annotations": [],
		"type": "AzureSqlTable",
		"schema": [
			{
				"name": "DPT_AUTO_KEY",
				"type": "decimal",
				"precision": 22,
				"scale": 0
			},
			{
				"name": "SYSCM_AUTO_KEY",
				"type": "decimal",
				"precision": 22,
				"scale": 0
			},
			{
				"name": "DIV_AUTO_KEY",
				"type": "decimal",
				"precision": 22,
				"scale": 0
			},
			{
				"name": "GLS_AUTO_KEY",
				"type": "decimal",
				"precision": 22,
				"scale": 0
			},
			{
				"name": "DEPT_NAME",
				"type": "nvarchar"
			},
			{
				"name": "SDF_DPT_001",
				"type": "nvarchar"
			}
		],
		"typeProperties": {
			"schema": "dbo",
			"table": "TESTENV_DEPARTMENT"
		}
	}
}